AUTHORS
ChangeLog
LICENSE
MANIFEST.in
README
_version.py
mirpyidl.c
mirpyidl.pyx
mirpyidlrpc.py
setup.py
doc_source/authors.rst
doc_source/conf.py
doc_source/development.rst
doc_source/development.rst~
doc_source/index.rst
doc_source/introduction.rst
doc_source/license.rst
doc_source/_templates/globaltoc.html
doc_source/autodoc/mirpyidl.rst
doc_source/autodoc/programmers_reference.rst
mirpyidl.egg-info/PKG-INFO
mirpyidl.egg-info/SOURCES.txt
mirpyidl.egg-info/dependency_links.txt
mirpyidl.egg-info/requires.txt
mirpyidl.egg-info/top_level.txt