Metadata-Version: 1.1
Name: mirpyidl
Version: 0.4.1
Summary: A library to call IDL (Interactive Data Language) from python.
Home-page: http://amicitas.bitbucket.org/mirpyidl/
Author: Novimir Antoniuk Pablant
Author-email: novimir.pablant@amicitas.com
License: MIT
Platform: UNKNOWN
Classifier: Development Status :: 4 - Beta
Classifier: License :: OSI Approved :: MIT License
Classifier: Topic :: Software Development :: Interpreters
Classifier: Programming Language :: Cython
Classifier: Programming Language :: Python
Classifier: Programming Language :: Other
